LICENSE
README.md
setup.py
fib_py/__init__.py
fib_py/cmd/__init__.py
fib_py/cmd/fib_numb.py
fib_py/fib_calcs/__init__.py
fib_py/fib_calcs/fib_number.py
fib_py/fib_calcs/fib_numbers.py
python_rust_fib.egg-info/PKG-INFO
python_rust_fib.egg-info/SOURCES.txt
python_rust_fib.egg-info/dependency_links.txt
python_rust_fib.egg-info/entry_points.txt
python_rust_fib.egg-info/requires.txt
python_rust_fib.egg-info/top_level.txt
tests/fib_py/__init__.py
tests/fib_py/cmd/__init__.py
tests/fib_py/cmd/fib_numb.py
tests/fib_py/fib_calcs/__init__.py
tests/fib_py/fib_calcs/test_fib_number.py
tests/fib_py/fib_calcs/test_fib_numbers.py