Metadata-Version: 2.1
Name: python-rust-fib
Version: 0.0.2
Summary: Calculates a Fibonacci number
Home-page: UNKNOWN
Author: Eduardo G. A. de Oliveira
Author-email: eduardo.g.amaral1997@gmail.com
License: UNKNOWN
Platform: UNKNOWN
Requires-Python: >=3
Provides-Extra: server
License-File: LICENSE
